macwinua/__init__.py
macwinua/contants.py
macwinua/exceptions.py
macwinua/ua.py
macwinua-0.1.3.dist-info/LICENSE.md
macwinua-0.1.3.dist-info/METADATA
macwinua-0.1.3.dist-info/WHEEL
macwinua-0.1.3.dist-info/RECORD
