Metadata-Version: 2.1
Name: macwinua
Version: 0.1.3
Summary: A library for generating realistic browser headers for macOS and Windows platforms — always the freshest Chrome headers.
Home-page: https://github.com/Nuung/MacWinUA.git
License: MIT
Author: Nuung
Author-email: qlgks1@naver.com
Requires-Python: >=3.10,<4.0
Classifier: Development Status :: 4 - Beta
Classifier: Intended Audience :: Developers
Classifier: License :: OSI Approved :: MIT License
Classifier: Programming Language :: Python :: 3
Classifier: Programming Language :: Python :: 3.10
Classifier: Programming Language :: Python :: 3.11
Classifier: Programming Language :: Python :: 3.12
Classifier: Programming Language :: Python :: 3.13
Project-URL: Repository, https://github.com/Nuung/MacWinUA.git
